{
   "pagination": {
     "results": 4,
     "page": 1,
     "page_size": 2,
     "pages": 2
   },
   "products" : [
      {
         "variant_option_three_value" : "",
         "variant_option_three_name" : "",
         "account_code_purchase" : "",
         "id" : "4ac27543-94b2-11e1-9ffa-4040dde94e2e",
         "variant_source_id" : "",
         "variant_option_two_value" : "",
         "image_large" : "https://trineodev.vendhq.com/images/placeholder/product/no-image-white-original.png",
         "source_id" : "",
         "brand_name" : "",
         "active" : true,
         "name" : "6 Pack Coffee",
         "description" : "",
         "price_book_entries" : [
            {
               "valid_from" : "",
               "max_units" : "",
               "product_id" : "4ac27543-94b2-11e1-9ffa-4040dde94e2e",
               "customer_group_id" : "6cbee822-3d5f-11e0-8697-4040f540b50a",
               "id" : "4ae383cd-94b2-11e1-9ffa-4040dde94e2e",
               "valid_to" : "",
               "outlet_id" : "",
               "display_retail_price_tax_inclusive" : "1",
               "price_book_name" : "General price book (All)",
               "tax" : 2.35,
               "outlet_name" : "",
               "customer_group_name" : "All Customers",
               "tax_rate" : "0.15",
               "price_book_id" : "6cc0a162-3d5f-11e0-8697-4040f540b50a",
               "tax_id" : "53b3501c-887c-102d-8a4b-a9cf13f17faa",
               "type" : "BASE",
               "price" : 15.65,
               "tax_name" : "NZ GST",
               "min_units" : ""
            }
         ],
         "tax_rate" : 0.15,
         "handle" : "6PackCoffee",
         "updated_at" : "2012-05-02 23:55:10",
         "price" : 15.65,
         "type" : "",
         "account_code_sales" : "",
         "sku" : "10002",
         "brand_id" : "",
         "variant_option_one_name" : "",
         "supplier_code" : "",
         "inventory" : [],
         "supply_price" : "0.00",
         "display_retail_price_tax_inclusive" : "1",
         "tax" : 2.35,
         "tags" : "",
         "image" : "https://trineodev.vendhq.com/images/placeholder/product/no-image-white-thumb.png",
         "variant_option_one_value" : "",
         "supplier_name" : "",
         "deleted_at" : "",
         "variant_parent_id" : "",
         "tax_id" : "53b3501c-887c-102d-8a4b-a9cf13f17faa",
         "tax_name" : "NZ GST",
         "variant_option_two_name" : ""
      },
      {
         "variant_option_three_value" : "Red",
         "variant_option_three_name" : "Colour",
         "account_code_purchase" : "",
         "id" : "4b44588b-94b2-11e1-9ffa-4040dde94e2e",
         "variant_source_id" : "",
         "variant_option_two_value" : "",
         "image_large" : "https://trineodev.vendhq.com/images/placeholder/product/no-image-white-original.png",
         "source_id" : "",
         "brand_name" : "My Coffee Shop",
         "active" : true,
         "name" : "Bacon and Eggs / Large / Red",
         "description" : "<p>Middle bacon with 2 freerange eggs cooked in your style on multi grain bread</p>",
         "price_book_entries" : [
            {
               "valid_from" : "",
               "max_units" : "",
               "product_id" : "4b44588b-94b2-11e1-9ffa-4040dde94e2e",
               "customer_group_id" : "6cbee822-3d5f-11e0-8697-4040f540b50a",
               "id" : "4b6eb246-94b2-11e1-9ffa-4040dde94e2e",
               "valid_to" : "",
               "outlet_id" : "",
               "display_retail_price_tax_inclusive" : "1",
               "price_book_name" : "General price book (All)",
               "tax" : 3.85,
               "outlet_name" : "",
               "customer_group_name" : "All Customers",
               "tax_rate" : "0.15",
               "price_book_id" : "6cc0a162-3d5f-11e0-8697-4040f540b50a",
               "tax_id" : "53b3501c-887c-102d-8a4b-a9cf13f17faa",
               "type" : "BASE",
               "price" : 25.69,
               "tax_name" : "NZ GST",
               "min_units" : ""
            }
         ],
         "tax_rate" : 0.15,
         "handle" : "1204",
         "updated_at" : "2012-05-02 23:55:11",
         "price" : 25.69,
         "type" : "General",
         "account_code_sales" : "",
         "sku" : "1204",
         "brand_id" : "4b2cb818-94b2-11e1-9ffa-4040dde94e2e",
         "variant_option_one_name" : "Color",
         "supplier_code" : "BDVT",
         "inventory" : [],
         "supply_price" : "0.00",
         "display_retail_price_tax_inclusive" : "1",
         "tax" : 3.85,
         "tags" : "Brunch, Breakfast, Cabinet, Bacon and Eggs",
         "image" : "https://trineodev.vendhq.com/images/placeholder/product/no-image-white-thumb.png",
         "variant_option_one_value" : "Large",
         "supplier_name" : "Bidvest",
         "deleted_at" : "",
         "variant_parent_id" : "",
         "tax_id" : "53b3501c-887c-102d-8a4b-a9cf13f17faa",
         "tax_name" : "NZ GST",
         "variant_option_two_name" : ""
      }
   ]
}
